{"contributors": null, "truncated": false, "text": "@MaanImranKhan @calipette it seems you missed that one among many others: http://t.co/FjKAfp5fs7", "in_reply_to_status_id": 553567716414484481, "id": 553574050032025600, "favorite_count": 0, "source": "<a href=\"http://twitter.com\" rel=\"nofollow\">Twitter Web Client</a>", "retweeted": false, "coordinates": null, "entities": {"symbols": [], "user_mentions": [{"id": 893836951, "indices": [0, 14], "id_str": "893836951", "screen_name": "MaanImranKhan", "name": "Maan Imran Khan"}, {"id": 223382695, "indices": [15, 25], "id_str": "223382695", "screen_name": "calipette", "name": "Beatrice S."}], "hashtags": [], "urls": [{"url": "http://t.co/FjKAfp5fs7", "indices": [74, 96], "expanded_url": "http://www.amazon.fr/Charlie-hebdo-n%C2%B0416-hitler-youpins/dp/B003X9MJOU", "display_url": "amazon.fr/Charlie-hebdo-\u2026"}]}, "in_reply_to_screen_name": "MaanImranKhan", "id_str": "553574050032025600", "retweet_count": 0, "in_reply_to_user_id": 893836951, "favorited": false, "user": {"follow_request_sent": false, "profile_use_background_image": true, "profile_text_color": "333333", "default_profile_image": false, "id": 28205604, "profile_background_image_url_https": "https://abs.twimg.com/images/themes/theme7/bg.gif", "verified": false, "profile_location": null, "profile_image_url_https": "https://pbs.twimg.com/profile_images/538340718918369280/J0Ut2JN9_normal.jpeg", "profile_sidebar_fill_color": "F3F3F3", "entities": {"url": {"urls": [{"url": "http://t.co/I4sgMfX6ka", "indices": [0, 22], "expanded_url": "http://soyezbenis.ca", "display_url": "soyezbenis.ca"}]}, "description": {"urls": []}}, "followers_count": 1181, "profile_sidebar_border_color": "DFDFDF", "id_str": "28205604", "profile_background_color": "EBEBEB", "listed_count": 32, "is_translation_enabled": false, "utc_offset": 3600, "statuses_count": 16078, "description": "Juriste et adh\u00e9rent #TeamCatho #ProLife #Veilleurs #TeamJuriste #TeamEMLyon #Centriste", "friends_count": 665, "location": "Laval", "profile_link_color": "990000", "profile_image_url": "http://pbs.twimg.com/profile_images/538340718918369280/J0Ut2JN9_normal.jpeg", "following": false, "geo_enabled": false, "profile_background_image_url": "http://abs.twimg.com/images/themes/theme7/bg.gif", "name": "Jean Dumant", "lang": "fr", "profile_background_tile": false, "favourites_count": 2551, "screen_name": "JeanDumant", "notifications": false, "url": "http://t.co/I4sgMfX6ka", "created_at": "Wed Apr 01 21:50:36 +0000 2009", "contributors_enabled": false, "time_zone": "Paris", "protected": false, "default_profile": false, "is_translator": false}, "geo": null, "in_reply_to_user_id_str": "893836951", "possibly_sensitive": false, "lang": "en", "created_at": "Fri Jan 09 15:28:33 +0000 2015", "in_reply_to_status_id_str": "553567716414484481", "place": null}
