{"contributors": null, "truncated": false, "text": "@AlexAllTimeLow scary situation hopefully things get solved", "in_reply_to_status_id": 544480083982168064, "id": 544480249715916800, "favorite_count": 0, "source": "<a href=\"http://twitter.com/download/iphone\" rel=\"nofollow\">Twitter for iPhone</a>", "retweeted": false, "coordinates": null, "entities": {"symbols": [], "user_mentions": [{"id": 18734884, "indices": [0, 15], "id_str": "18734884", "screen_name": "AlexAllTimeLow", "name": "Alexander William"}], "hashtags": [], "urls": []}, "in_reply_to_screen_name": "AlexAllTimeLow", "id_str": "544480249715916800", "retweet_count": 0, "in_reply_to_user_id": 18734884, "favorited": false, "user": {"follow_request_sent": false, "profile_use_background_image": false, "profile_text_color": "000000", "default_profile_image": false, "id": 1542338576, "profile_background_image_url_https": "https://abs.twimg.com/images/themes/theme1/bg.png", "verified": false, "profile_location": null, "profile_image_url_https": "https://pbs.twimg.com/profile_images/545065060469846016/K0OwNLbQ_normal.jpeg", "profile_sidebar_fill_color": "000000", "entities": {"url": {"urls": [{"url": "https://t.co/DuRrjKc6UY", "indices": [0, 23], "expanded_url": "https://twitter.com/mikeyscupcakes_/status/534047612748718080", "display_url": "twitter.com/mikeyscupcakes\u2026"}]}, "description": {"urls": []}}, "followers_count": 7564, "profile_sidebar_border_color": "000000", "id_str": "1542338576", "profile_background_color": "000000", "listed_count": 50, "is_translation_enabled": false, "utc_offset": null, "statuses_count": 36028, "description": "\u275di feel a little lost in this world\u275e \u263c", "friends_count": 3918, "location": "\u2639/4 \u2639/5\u2728 Chicago", "profile_link_color": "9266CC", "profile_image_url": "http://pbs.twimg.com/profile_images/545065060469846016/K0OwNLbQ_normal.jpeg", "following": false, "geo_enabled": true, "profile_banner_url": "https://pbs.twimg.com/profile_banners/1542338576/1418788555", "profile_background_image_url": "http://abs.twimg.com/images/themes/theme1/bg.png", "name": "\u2620Leslie |226 days\u2620", "lang": "en", "profile_background_tile": false, "favourites_count": 7729, "screen_name": "MikeysCupcakes_", "notifications": false, "url": "https://t.co/DuRrjKc6UY", "created_at": "Mon Jun 24 02:43:14 +0000 2013", "contributors_enabled": false, "time_zone": null, "protected": false, "default_profile": false, "is_translator": false}, "geo": null, "in_reply_to_user_id_str": "18734884", "lang": "en", "created_at": "Mon Dec 15 13:13:02 +0000 2014", "in_reply_to_status_id_str": "544480083982168064", "place": null}
