{"contributors": null, "truncated": false, "text": "@Mafroor1 @RT_com Most likely Putins Russia Maduros Venezuela or the Ayatollas Iran...", "in_reply_to_status_id": 580322663475740673, "id": 580325170092589056, "favorite_count": 0, "source": "<a href=\"http://twitter.com/download/android\" rel=\"nofollow\">Twitter for Android</a>", "retweeted": false, "coordinates": null, "entities": {"symbols": [], "user_mentions": [{"id": 938671448, "indices": [0, 9], "id_str": "938671448", "screen_name": "Mafroor1", "name": "Khas Khaki"}, {"id": 64643056, "indices": [10, 17], "id_str": "64643056", "screen_name": "RT_com", "name": "RT"}], "hashtags": [], "urls": []}, "in_reply_to_screen_name": "Mafroor1", "id_str": "580325170092589056", "retweet_count": 0, "in_reply_to_user_id": 938671448, "favorited": false, "user": {"follow_request_sent": false, "profile_use_background_image": true, "profile_text_color": "333333", "default_profile_image": false, "id": 2263883537, "profile_background_image_url_https": "https://abs.twimg.com/images/themes/theme1/bg.png", "verified": false, "profile_location": null, "profile_image_url_https": "https://pbs.twimg.com/profile_images/540771029585780736/c2G0619Q_normal.jpeg", "profile_sidebar_fill_color": "DDEEF6", "entities": {"description": {"urls": []}}, "followers_count": 64, "profile_sidebar_border_color": "C0DEED", "id_str": "2263883537", "profile_background_color": "C0DEED", "listed_count": 11, "is_translation_enabled": false, "utc_offset": null, "statuses_count": 6181, "description": "", "friends_count": 8, "location": "", "profile_link_color": "0084B4", "profile_image_url": "http://pbs.twimg.com/profile_images/540771029585780736/c2G0619Q_normal.jpeg", "following": false, "geo_enabled": true, "profile_background_image_url": "http://abs.twimg.com/images/themes/theme1/bg.png", "name": "muthoni kimathi", "lang": "en", "profile_background_tile": false, "favourites_count": 22, "screen_name": "muthonikimathi", "notifications": false, "url": null, "created_at": "Sun Jan 05 17:02:23 +0000 2014", "contributors_enabled": false, "time_zone": null, "protected": false, "default_profile": true, "is_translator": false}, "geo": null, "in_reply_to_user_id_str": "938671448", "lang": "es", "created_at": "Tue Mar 24 11:07:57 +0000 2015", "in_reply_to_status_id_str": "580322663475740673", "place": null}
