{"contributors": null, "truncated": false, "text": "@MichaelSkolnik Actually it does, and is in the 1st amendment,", "in_reply_to_status_id": 499705963126202368, "id": 499706905393397760, "favorite_count": 0, "source": "<a href=\"http://twitter.com\" rel=\"nofollow\">Twitter Web Client</a>", "retweeted": false, "coordinates": null, "entities": {"symbols": [], "user_mentions": [{"id": 24165761, "indices": [0, 15], "id_str": "24165761", "screen_name": "MichaelSkolnik", "name": "Michael Skolnik"}], "hashtags": [], "urls": []}, "in_reply_to_screen_name": "MichaelSkolnik", "id_str": "499706905393397760", "retweet_count": 0, "in_reply_to_user_id": 24165761, "favorited": false, "user": {"follow_request_sent": false, "profile_use_background_image": true, "default_profile_image": false, "id": 817875133, "profile_background_image_url_https": "https://pbs.twimg.com/profile_background_images/754890980/772a8a842e7648827c1f11d9ed7b9475.jpeg", "verified": false, "profile_text_color": "333333", "profile_image_url_https": "https://pbs.twimg.com/profile_images/3062870264/3c7d6c4c6f527140526bd518d51cfdb2_normal.png", "profile_sidebar_fill_color": "DDEEF6", "entities": {"url": {"urls": [{"url": "http://t.co/RazPzZi7jl", "indices": [0, 22], "expanded_url": "http://www.sweetherbalcoop.com", "display_url": "sweetherbalcoop.com"}]}, "description": {"urls": []}}, "followers_count": 291, "profile_sidebar_border_color": "FFFFFF", "id_str": "817875133", "profile_background_color": "FFFFFF", "listed_count": 9, "is_translation_enabled": false, "utc_offset": -25200, "statuses_count": 416, "description": "Medical Marijuana ( MMJ ) Dispensary located in the Rainier Valley. Open 7 Days a week from 10am to 8pm. Tweet or Give us a call (206) 760-6105", "friends_count": 410, "location": "Seattle, WA (Columbia City)", "profile_link_color": "93A644", "profile_image_url": "http://pbs.twimg.com/profile_images/3062870264/3c7d6c4c6f527140526bd518d51cfdb2_normal.png", "following": false, "geo_enabled": true, "profile_banner_url": "https://pbs.twimg.com/profile_banners/817875133/1357276746", "profile_background_image_url": "http://pbs.twimg.com/profile_background_images/754890980/772a8a842e7648827c1f11d9ed7b9475.jpeg", "screen_name": "SweetHerbalCoOp", "lang": "en", "profile_background_tile": true, "favourites_count": 3, "name": "Sweet Herbal Co-Op", "notifications": false, "url": "http://t.co/RazPzZi7jl", "created_at": "Tue Sep 11 17:49:44 +0000 2012", "contributors_enabled": false, "time_zone": "Arizona", "protected": false, "default_profile": false, "is_translator": false}, "geo": null, "in_reply_to_user_id_str": "24165761", "lang": "en", "created_at": "Wed Aug 13 23:59:45 +0000 2014", "in_reply_to_status_id_str": "499705963126202368", "place": null}
