{"contributors":null,"truncated":false,"text":"@Will_Antonin @stegersaurus you mean the la times story 14 hours ago? http:\/\/t.co\/8iw2WIdKjk we are still talking.","in_reply_to_status_id":553214726629781505,"id":553223370867625985,"favorite_count":0,"source":"<a href=\"http:\/\/twitter.com\/download\/iphone\" rel=\"nofollow\">Twitter for iPhone<\/a>","retweeted":false,"coordinates":null,"entities":{"symbols":[],"user_mentions":[{"id":520011678,"indices":[0,13],"id_str":"520011678","screen_name":"Will_Antonin","name":"Will Antonin"},{"id":21771755,"indices":[14,27],"id_str":"21771755","screen_name":"stegersaurus","name":"isabella steger"}],"hashtags":[],"urls":[{"url":"http:\/\/t.co\/8iw2WIdKjk","indices":[70,92],"expanded_url":"http:\/\/www.latimes.com\/opinion\/op-ed\/la-oe-sam-bring-back-our-girls-20150108-story.html","display_url":"latimes.com\/opinion\/op-ed\/\u2026"}]},"in_reply_to_screen_name":"Will_Antonin","id_str":"553223370867625985","retweet_count":0,"in_reply_to_user_id":520011678,"favorited":false,"user":{"follow_request_sent":false,"profile_use_background_image":true,"profile_text_color":"333333","default_profile_image":false,"id":15730804,"profile_background_image_url_https":"https:\/\/pbs.twimg.com\/profile_background_images\/517092615007633408\/RjADfGLU.jpeg","verified":false,"profile_location":null,"profile_image_url_https":"https:\/\/pbs.twimg.com\/profile_images\/570219061268717568\/ES4imy_d_normal.jpeg","profile_sidebar_fill_color":"EADEAA","entities":{"url":{"urls":[{"url":"http:\/\/t.co\/pCMuulSkUh","indices":[0,22],"expanded_url":"http:\/\/travelhominid.launchrock.com","display_url":"travelhominid.launchrock.com"}]},"description":{"urls":[]}},"followers_count":6328,"profile_sidebar_border_color":"FFFFFF","id_str":"15730804","profile_background_color":"8B542B","listed_count":469,"is_translation_enabled":false,"utc_offset":-28800,"statuses_count":46033,"description":"Africa; travel; mountaineering; tech; bitcoin; vc; coffee; former marketing manager @microsoft & @starbucks; building University of Hong incubator program","friends_count":3634,"location":"All 7 continents","profile_link_color":"ABB8C2","profile_image_url":"http:\/\/pbs.twimg.com\/profile_images\/570219061268717568\/ES4imy_d_normal.jpeg","following":false,"geo_enabled":true,"profile_banner_url":"https:\/\/pbs.twimg.com\/profile_banners\/15730804\/1421458841","profile_background_image_url":"http:\/\/pbs.twimg.com\/profile_background_images\/517092615007633408\/RjADfGLU.jpeg","name":"Douglas Crets","lang":"en","profile_background_tile":true,"favourites_count":5431,"screen_name":"DouglasCrets","notifications":false,"url":"http:\/\/t.co\/pCMuulSkUh","created_at":"Tue Aug 05 01:50:00 +0000 2008","contributors_enabled":false,"time_zone":"Pacific Time (US & Canada)","protected":false,"default_profile":false,"is_translator":false},"geo":null,"in_reply_to_user_id_str":"520011678","possibly_sensitive":false,"lang":"en","created_at":"Thu Jan 08 16:15:04 +0000 2015","in_reply_to_status_id_str":"553214726629781505","place":null}