{"contributors":null,"truncated":false,"text":"@cnnbrk Good riddance!","in_reply_to_status_id":553590427216248832,"id":553590771325345792,"favorite_count":3,"source":"<a href=\"http:\/\/twitter.com\/download\/android\" rel=\"nofollow\">Twitter for Android<\/a>","retweeted":false,"coordinates":null,"entities":{"symbols":[],"user_mentions":[{"id":428333,"indices":[0,7],"id_str":"428333","screen_name":"cnnbrk","name":"CNN Breaking News"}],"hashtags":[],"urls":[]},"in_reply_to_screen_name":"cnnbrk","id_str":"553590771325345792","retweet_count":0,"in_reply_to_user_id":428333,"favorited":false,"user":{"follow_request_sent":false,"profile_use_background_image":true,"profile_text_color":"3C3940","default_profile_image":false,"id":23659772,"profile_background_image_url_https":"https:\/\/pbs.twimg.com\/profile_background_images\/507855821414227971\/hiQHMvjc.jpeg","verified":false,"profile_location":null,"profile_image_url_https":"https:\/\/pbs.twimg.com\/profile_images\/589094355501244417\/kW1Uvv2O_normal.jpg","profile_sidebar_fill_color":"95E8EC","entities":{"description":{"urls":[]}},"followers_count":20593,"profile_sidebar_border_color":"FFFFFF","id_str":"23659772","profile_background_color":"0062B8","listed_count":21,"is_translation_enabled":false,"utc_offset":null,"statuses_count":15222,"description":"Easily distracted by shiny objects\u2026","friends_count":15844,"location":"","profile_link_color":"B88400","profile_image_url":"http:\/\/pbs.twimg.com\/profile_images\/589094355501244417\/kW1Uvv2O_normal.jpg","following":false,"geo_enabled":false,"profile_banner_url":"https:\/\/pbs.twimg.com\/profile_banners\/23659772\/1413723720","profile_background_image_url":"http:\/\/pbs.twimg.com\/profile_background_images\/507855821414227971\/hiQHMvjc.jpeg","name":"Angel \u2606 Russo ","lang":"en","profile_background_tile":true,"favourites_count":13317,"screen_name":"Angel__Angelica","notifications":false,"url":null,"created_at":"Tue Mar 10 21:21:54 +0000 2009","contributors_enabled":false,"time_zone":null,"protected":false,"default_profile":false,"is_translator":false},"geo":null,"in_reply_to_user_id_str":"428333","lang":"en","created_at":"Fri Jan 09 16:34:59 +0000 2015","in_reply_to_status_id_str":"553590427216248832","place":null}