{"contributors":null,"truncated":false,"text":"@vancouverboomer @LukeRussert @ott_deb duh huh?","in_reply_to_status_id":524998667485601792,"id":525010966443225088,"favorite_count":1,"source":"<a href=\"http:\/\/twitter.com\/download\/android\" rel=\"nofollow\">Twitter for Android<\/a>","retweeted":false,"coordinates":null,"entities":{"symbols":[],"user_mentions":[{"id":16351985,"indices":[0,16],"id_str":"16351985","screen_name":"vancouverboomer","name":"vancouverboomer"},{"id":21220931,"indices":[17,29],"id_str":"21220931","screen_name":"LukeRussert","name":"Luke Russert"},{"id":1369986619,"indices":[30,38],"id_str":"1369986619","screen_name":"ott_deb","name":"DJM"}],"hashtags":[],"urls":[]},"in_reply_to_screen_name":"vancouverboomer","id_str":"525010966443225088","retweet_count":0,"in_reply_to_user_id":16351985,"favorited":false,"user":{"follow_request_sent":false,"profile_use_background_image":true,"default_profile_image":false,"id":2748447515,"profile_background_image_url_https":"https:\/\/abs.twimg.com\/images\/themes\/theme1\/bg.png","verified":false,"profile_text_color":"333333","profile_image_url_https":"https:\/\/pbs.twimg.com\/profile_images\/530354588470497282\/z70oF_ns_normal.jpeg","profile_sidebar_fill_color":"DDEEF6","entities":{"description":{"urls":[]}},"followers_count":450,"profile_sidebar_border_color":"C0DEED","id_str":"2748447515","profile_background_color":"C0DEED","listed_count":6,"is_translation_enabled":false,"utc_offset":null,"statuses_count":3869,"description":"American, Vet of Iraq War, FireFighter, Father, Husband, Brother&Son. Most Fed up American! Ready to take point on new govt!","friends_count":357,"location":"","profile_link_color":"0084B4","profile_image_url":"http:\/\/pbs.twimg.com\/profile_images\/530354588470497282\/z70oF_ns_normal.jpeg","following":false,"geo_enabled":false,"profile_banner_url":"https:\/\/pbs.twimg.com\/profile_banners\/2748447515\/1408571095","profile_background_image_url":"http:\/\/abs.twimg.com\/images\/themes\/theme1\/bg.png","screen_name":"meileiend","lang":"en","profile_background_tile":false,"favourites_count":1777,"name":"david edwards","notifications":false,"url":null,"created_at":"Wed Aug 20 21:33:21 +0000 2014","contributors_enabled":false,"time_zone":null,"protected":false,"default_profile":true,"is_translator":false},"geo":null,"in_reply_to_user_id_str":"16351985","lang":"in","created_at":"Wed Oct 22 19:49:03 +0000 2014","in_reply_to_status_id_str":"524998667485601792","place":null}