{"contributors": null, "truncated": false, "text": "@iyad_elbaghdadi @rickardc87 My religion was no different  in 11 century  but its evolved  in the 21 Century IRA relised dialogue wins peace", "in_reply_to_status_id": 552805970536333314, "id": 552831841095651328, "favorite_count": 0, "source": "<a href=\"http://twitter.com/download/android\" rel=\"nofollow\">Twitter for Android</a>", "retweeted": false, "coordinates": null, "entities": {"symbols": [], "user_mentions": [{"id": 18725815, "indices": [0, 16], "id_str": "18725815", "screen_name": "iyad_elbaghdadi", "name": "Iyad El-Baghdadi"}, {"id": 219373341, "indices": [17, 28], "id_str": "219373341", "screen_name": "rickardc87", "name": "Craig Rickard"}], "hashtags": [], "urls": []}, "in_reply_to_screen_name": "iyad_elbaghdadi", "id_str": "552831841095651328", "retweet_count": 0, "in_reply_to_user_id": 18725815, "favorited": false, "user": {"follow_request_sent": false, "profile_use_background_image": true, "profile_text_color": "333333", "default_profile_image": false, "id": 163945249, "profile_background_image_url_https": "https://abs.twimg.com/images/themes/theme15/bg.png", "verified": false, "profile_location": null, "profile_image_url_https": "https://pbs.twimg.com/profile_images/458367396991213568/QGvWDRWd_normal.jpeg", "profile_sidebar_fill_color": "C0DFEC", "entities": {"description": {"urls": []}}, "followers_count": 1905, "profile_sidebar_border_color": "A8C7F7", "id_str": "163945249", "profile_background_color": "022330", "listed_count": 13, "is_translation_enabled": false, "utc_offset": 0, "statuses_count": 45522, "description": "Virgin star gazer father of 3 partner of Irene mad Spurs fan  Widnes Vikings", "friends_count": 1838, "location": "widnes", "profile_link_color": "0084B4", "profile_image_url": "http://pbs.twimg.com/profile_images/458367396991213568/QGvWDRWd_normal.jpeg", "following": false, "geo_enabled": true, "profile_background_image_url": "http://abs.twimg.com/images/themes/theme15/bg.png", "name": "DAVSPURS", "lang": "en", "profile_background_tile": false, "favourites_count": 940, "screen_name": "davspurs", "notifications": false, "url": null, "created_at": "Wed Jul 07 17:20:12 +0000 2010", "contributors_enabled": false, "time_zone": "London", "protected": false, "default_profile": false, "is_translator": false}, "geo": null, "in_reply_to_user_id_str": "18725815", "lang": "en", "created_at": "Wed Jan 07 14:19:16 +0000 2015", "in_reply_to_status_id_str": "552805970536333314", "place": null}
