{"contributors":null,"truncated":false,"text":"@dollyfostermini You genuinely believe the MCB is in league with these #UKIP'ish zealots?","in_reply_to_status_id":552802761163939840,"id":552817927179993089,"favorite_count":1,"source":"<a href=\"http:\/\/twitter.com\" rel=\"nofollow\">Twitter Web Client<\/a>","retweeted":false,"coordinates":null,"entities":{"symbols":[],"user_mentions":[{"id":297380638,"indices":[0,16],"id_str":"297380638","screen_name":"dollyfostermini","name":"SunderlandUKipMan"}],"hashtags":[{"indices":[71,76],"text":"UKIP"}],"urls":[]},"in_reply_to_screen_name":"dollyfostermini","id_str":"552817927179993089","retweet_count":0,"in_reply_to_user_id":297380638,"favorited":false,"user":{"follow_request_sent":false,"profile_use_background_image":false,"profile_text_color":"333333","default_profile_image":false,"id":2331625888,"profile_background_image_url_https":"https:\/\/pbs.twimg.com\/profile_background_images\/492979641083129857\/ZOr1-twg.png","verified":false,"profile_location":null,"profile_image_url_https":"https:\/\/pbs.twimg.com\/profile_images\/590387728094781440\/QVsMEnLE_normal.jpg","profile_sidebar_fill_color":"DDEEF6","entities":{"url":{"urls":[{"url":"http:\/\/t.co\/ohe67vczMj","indices":[0,22],"expanded_url":"http:\/\/tusc.org.uk","display_url":"tusc.org.uk"}]},"description":{"urls":[]}},"followers_count":319,"profile_sidebar_border_color":"FFFFFF","id_str":"2331625888","profile_background_color":"C3EAEB","listed_count":4,"is_translation_enabled":false,"utc_offset":0,"statuses_count":7400,"description":"Shop steward, #TUSC-SP, mutt, social animal. Passionate about cooking, film, music, and life generally. Still-recovering American.","friends_count":230,"location":"Red Star NE29","profile_link_color":"ABB8C2","profile_image_url":"http:\/\/pbs.twimg.com\/profile_images\/590387728094781440\/QVsMEnLE_normal.jpg","following":false,"geo_enabled":true,"profile_banner_url":"https:\/\/pbs.twimg.com\/profile_banners\/2331625888\/1420313155","profile_background_image_url":"http:\/\/pbs.twimg.com\/profile_background_images\/492979641083129857\/ZOr1-twg.png","name":"FamousINTLPlayboy","lang":"en","profile_background_tile":true,"favourites_count":4965,"screen_name":"ReverseCutsNow","notifications":false,"url":"http:\/\/t.co\/ohe67vczMj","created_at":"Sat Feb 08 08:32:47 +0000 2014","contributors_enabled":false,"time_zone":"London","protected":false,"default_profile":false,"is_translator":false},"geo":null,"in_reply_to_user_id_str":"297380638","lang":"en","created_at":"Wed Jan 07 13:23:59 +0000 2015","in_reply_to_status_id_str":"552802761163939840","place":null}