{"contributors": null, "truncated": false, "text": "@MashableNews @mashable Hearts and prayers are with the victims, families and French people - we are all Parisians today. #CharlieHebdo", "in_reply_to_status_id": 552829904396775425, "id": 552841426032414720, "favorite_count": 0, "source": "<a href=\"http://twitter.com\" rel=\"nofollow\">Twitter Web Client</a>", "retweeted": false, "coordinates": null, "entities": {"symbols": [], "user_mentions": [{"id": 372502604, "indices": [0, 13], "id_str": "372502604", "screen_name": "MashableNews", "name": "Mashable News"}, {"id": 972651, "indices": [14, 23], "id_str": "972651", "screen_name": "mashable", "name": "Mashable"}], "hashtags": [{"indices": [122, 135], "text": "CharlieHebdo"}], "urls": []}, "in_reply_to_screen_name": "MashableNews", "id_str": "552841426032414720", "retweet_count": 0, "in_reply_to_user_id": 372502604, "favorited": false, "user": {"follow_request_sent": false, "profile_use_background_image": true, "profile_text_color": "333333", "default_profile_image": false, "id": 110306778, "profile_background_image_url_https": "https://abs.twimg.com/images/themes/theme14/bg.gif", "verified": false, "profile_location": null, "profile_image_url_https": "https://pbs.twimg.com/profile_images/556911196511539202/VWX5ltcT_normal.jpeg", "profile_sidebar_fill_color": "C0DFEC", "entities": {"url": {"urls": [{"url": "http://t.co/ar4xX11Ye0", "indices": [0, 22], "expanded_url": "http://starrPR.com", "display_url": "starrPR.com"}]}, "description": {"urls": []}}, "followers_count": 59, "profile_sidebar_border_color": "A8C7F7", "id_str": "110306778", "profile_background_color": "3B94D9", "listed_count": 4, "is_translation_enabled": false, "utc_offset": -18000, "statuses_count": 225, "description": "Parrot whisperer - digs martinis, home cooking, fine art, bossa nova & ocean air. I'm in public relations & communications & the Managing Director of Starr PR.", "friends_count": 76, "location": "Miami, Florida  USA", "profile_link_color": "3B94D9", "profile_image_url": "http://pbs.twimg.com/profile_images/556911196511539202/VWX5ltcT_normal.jpeg", "following": false, "geo_enabled": true, "profile_banner_url": "https://pbs.twimg.com/profile_banners/110306778/1420750205", "profile_background_image_url": "http://abs.twimg.com/images/themes/theme14/bg.gif", "name": "RJ Starr", "lang": "en", "profile_background_tile": false, "favourites_count": 2, "screen_name": "miami_rj", "notifications": false, "url": "http://t.co/ar4xX11Ye0", "created_at": "Mon Feb 01 02:56:24 +0000 2010", "contributors_enabled": false, "time_zone": "Eastern Time (US & Canada)", "protected": false, "default_profile": false, "is_translator": false}, "geo": null, "in_reply_to_user_id_str": "372502604", "lang": "en", "created_at": "Wed Jan 07 14:57:21 +0000 2015", "in_reply_to_status_id_str": "552829904396775425", "place": null}
