{"contributors": null, "truncated": false, "text": "@CBCAlerts MP Bernard Trottier tweeting that suspect shot &amp; killed.", "in_reply_to_status_id": 524935085863481344, "id": 524936259190665216, "favorite_count": 0, "source": "<a href=\"http://twitter.com\" rel=\"nofollow\">Twitter Web Client</a>", "retweeted": false, "coordinates": null, "entities": {"symbols": [], "user_mentions": [{"id": 19038934, "indices": [0, 10], "id_str": "19038934", "screen_name": "CBCAlerts", "name": "CBC News Alerts"}], "hashtags": [], "urls": []}, "in_reply_to_screen_name": "CBCAlerts", "id_str": "524936259190665216", "retweet_count": 0, "in_reply_to_user_id": 19038934, "favorited": false, "user": {"follow_request_sent": false, "profile_use_background_image": true, "default_profile_image": false, "id": 370424351, "profile_background_image_url_https": "https://abs.twimg.com/images/themes/theme12/bg.gif", "verified": false, "profile_text_color": "0C3E53", "profile_image_url_https": "https://pbs.twimg.com/profile_images/1555027359/clean_logo_normal.png", "profile_sidebar_fill_color": "FFF7CC", "entities": {"url": {"urls": [{"url": "http://t.co/CHJXcPHwAX", "indices": [0, 22], "expanded_url": "http://www.hraskme.com", "display_url": "hraskme.com"}]}, "description": {"urls": []}}, "followers_count": 1455, "profile_sidebar_border_color": "F2E195", "id_str": "370424351", "profile_background_color": "BADFCD", "listed_count": 61, "is_translation_enabled": false, "utc_offset": -14400, "statuses_count": 3261, "description": "40 yrs experience, 10 as an army officer & 30 as an HR mgr. Thru HRAskMe I aim to provide HR advice that will be enjoyable, memorable, relevant and applicable.", "friends_count": 2001, "location": "Toronto", "profile_link_color": "FF0000", "profile_image_url": "http://pbs.twimg.com/profile_images/1555027359/clean_logo_normal.png", "following": false, "geo_enabled": false, "profile_banner_url": "https://pbs.twimg.com/profile_banners/370424351/1399645857", "profile_background_image_url": "http://abs.twimg.com/images/themes/theme12/bg.gif", "screen_name": "HRAskMe", "lang": "en", "profile_background_tile": false, "favourites_count": 3, "name": "Martin Birt", "notifications": false, "url": "http://t.co/CHJXcPHwAX", "created_at": "Fri Sep 09 00:38:29 +0000 2011", "contributors_enabled": false, "time_zone": "Eastern Time (US & Canada)", "protected": false, "default_profile": false, "is_translator": false}, "geo": null, "in_reply_to_user_id_str": "19038934", "lang": "en", "created_at": "Wed Oct 22 14:52:11 +0000 2014", "in_reply_to_status_id_str": "524935085863481344", "place": null}
