{"contributors":null,"truncated":false,"text":"@PrestonMitchum @donlemon lol","in_reply_to_status_id":500339591392817152,"id":500345397282631680,"favorite_count":0,"source":"<a href=\"http:\/\/twitter.com\/download\/iphone\" rel=\"nofollow\">Twitter for iPhone<\/a>","retweeted":false,"coordinates":null,"entities":{"symbols":[],"user_mentions":[{"id":584797578,"indices":[0,15],"id_str":"584797578","screen_name":"PrestonMitchum","name":"PrestonMitchum"},{"id":16051471,"indices":[16,25],"id_str":"16051471","screen_name":"donlemon","name":"Don Lemon"}],"hashtags":[],"urls":[]},"in_reply_to_screen_name":"PrestonMitchum","id_str":"500345397282631680","retweet_count":0,"in_reply_to_user_id":584797578,"favorited":false,"user":{"follow_request_sent":false,"profile_use_background_image":true,"default_profile_image":false,"id":308334301,"profile_background_image_url_https":"https:\/\/pbs.twimg.com\/profile_background_images\/726897696\/e694402eb7ea0c198c8e310f8763e3d3.jpeg","verified":false,"profile_text_color":"BD3D85","profile_image_url_https":"https:\/\/pbs.twimg.com\/profile_images\/531465705750020096\/h1wuX3nB_normal.jpeg","profile_sidebar_fill_color":"1F2224","entities":{"url":{"urls":[{"url":"http:\/\/t.co\/RgB9DP4NXu","indices":[0,22],"expanded_url":"http:\/\/www.facebook.com\/shamarie20","display_url":"facebook.com\/shamarie20"}]},"description":{"urls":[]}},"followers_count":82,"profile_sidebar_border_color":"FFFFFF","id_str":"308334301","profile_background_color":"141413","listed_count":1,"is_translation_enabled":false,"utc_offset":-25200,"statuses_count":1805,"description":"Live Beautifully \u2666 Dream Passionately \u2666 Love Completely","friends_count":125,"location":"CA","profile_link_color":"5C5458","profile_image_url":"http:\/\/pbs.twimg.com\/profile_images\/531465705750020096\/h1wuX3nB_normal.jpeg","following":false,"geo_enabled":true,"profile_banner_url":"https:\/\/pbs.twimg.com\/profile_banners\/308334301\/1400713087","profile_background_image_url":"http:\/\/pbs.twimg.com\/profile_background_images\/726897696\/e694402eb7ea0c198c8e310f8763e3d3.jpeg","screen_name":"Sha_Moore","lang":"en","profile_background_tile":true,"favourites_count":2066,"name":"Shanelle Moore","notifications":false,"url":"http:\/\/t.co\/RgB9DP4NXu","created_at":"Tue May 31 07:03:24 +0000 2011","contributors_enabled":false,"time_zone":"Pacific Time (US & Canada)","protected":false,"default_profile":false,"is_translator":false},"geo":null,"in_reply_to_user_id_str":"584797578","lang":"und","created_at":"Fri Aug 15 18:16:53 +0000 2014","in_reply_to_status_id_str":"500339591392817152","place":null}