{"contributors": null, "truncated": false, "text": "@selfstyledsiren @onwards62 Take care Farran as you will see from tweets people can be so bigoted especially when scared &amp; angry. :(", "in_reply_to_status_id": 552813590919778304, "id": 552871691945512960, "favorite_count": 2, "source": "<a href=\"http://twitter.com\" rel=\"nofollow\">Twitter Web Client</a>", "retweeted": false, "coordinates": null, "entities": {"symbols": [], "user_mentions": [{"id": 122557484, "indices": [0, 16], "id_str": "122557484", "screen_name": "selfstyledsiren", "name": "Farran Nehme"}, {"id": 1051463708, "indices": [17, 27], "id_str": "1051463708", "screen_name": "onwards62", "name": "lilyrose"}], "hashtags": [], "urls": []}, "in_reply_to_screen_name": "selfstyledsiren", "id_str": "552871691945512960", "retweet_count": 1, "in_reply_to_user_id": 122557484, "favorited": false, "user": {"follow_request_sent": false, "profile_use_background_image": false, "profile_text_color": "3FD85B", "default_profile_image": false, "id": 19656438, "profile_background_image_url_https": "https://pbs.twimg.com/profile_background_images/432988541690208256/kjy0UuYk.jpeg", "verified": false, "profile_location": null, "profile_image_url_https": "https://pbs.twimg.com/profile_images/539014739829858304/ZhP9WWv1_normal.jpeg", "profile_sidebar_fill_color": "0F0F0F", "entities": {"url": {"urls": [{"url": "http://t.co/piBVwgnEia", "indices": [0, 22], "expanded_url": "http://about.me/banana_the_poet", "display_url": "about.me/banana_the_poet"}]}, "description": {"urls": []}}, "followers_count": 3238, "profile_sidebar_border_color": "333333", "id_str": "19656438", "profile_background_color": "000000", "listed_count": 236, "is_translation_enabled": false, "utc_offset": 7200, "statuses_count": 22162, "description": "I'm a poet... Everything you say or do may end up in a poem. But nobody will understand it - so you are safe ;)", "friends_count": 2587, "location": "South Wales, UK", "profile_link_color": "B9B9B9", "profile_image_url": "http://pbs.twimg.com/profile_images/539014739829858304/ZhP9WWv1_normal.jpeg", "following": false, "geo_enabled": false, "profile_banner_url": "https://pbs.twimg.com/profile_banners/19656438/1417457194", "profile_background_image_url": "http://pbs.twimg.com/profile_background_images/432988541690208256/kjy0UuYk.jpeg", "name": "Michele Brenton", "lang": "en", "profile_background_tile": false, "favourites_count": 134, "screen_name": "banana_the_poet", "notifications": false, "url": "http://t.co/piBVwgnEia", "created_at": "Wed Jan 28 15:22:45 +0000 2009", "contributors_enabled": false, "time_zone": "Athens", "protected": false, "default_profile": false, "is_translator": false}, "geo": null, "in_reply_to_user_id_str": "122557484", "lang": "en", "created_at": "Wed Jan 07 16:57:37 +0000 2015", "in_reply_to_status_id_str": "552813590919778304", "place": null}
