{"contributors": null, "truncated": false, "text": "@mashable @uber I love the service but this is classless", "in_reply_to_status_id": 544314234541469696, "id": 544314872985423872, "favorite_count": 0, "source": "<a href=\"http://twitter.com/download/android\" rel=\"nofollow\">Twitter for Android</a>", "retweeted": false, "coordinates": null, "entities": {"symbols": [], "user_mentions": [{"id": 972651, "indices": [0, 9], "id_str": "972651", "screen_name": "mashable", "name": "Mashable"}, {"id": 19103481, "indices": [10, 15], "id_str": "19103481", "screen_name": "Uber", "name": "Uber"}], "hashtags": [], "urls": []}, "in_reply_to_screen_name": "mashable", "id_str": "544314872985423872", "retweet_count": 0, "in_reply_to_user_id": 972651, "favorited": false, "user": {"follow_request_sent": false, "profile_use_background_image": true, "profile_text_color": "333333", "default_profile_image": false, "id": 34660897, "profile_background_image_url_https": "https://abs.twimg.com/images/themes/theme1/bg.png", "verified": false, "profile_location": null, "profile_image_url_https": "https://pbs.twimg.com/profile_images/1181734629/twitter_normal.jpg", "profile_sidebar_fill_color": "DDEEF6", "entities": {"description": {"urls": []}}, "followers_count": 407, "profile_sidebar_border_color": "C0DEED", "id_str": "34660897", "profile_background_color": "C0DEED", "listed_count": 17, "is_translation_enabled": false, "utc_offset": -25200, "statuses_count": 8138, "description": "ex pat Aussie living in Calgary ,husband, father,lover of golf,wine,tech & movies. Principal, Global Technical Partnerships - @AmazonVideo - Opinions are my own", "friends_count": 773, "location": "Calgary ", "profile_link_color": "0084B4", "profile_image_url": "http://pbs.twimg.com/profile_images/1181734629/twitter_normal.jpg", "following": false, "geo_enabled": true, "profile_background_image_url": "http://abs.twimg.com/images/themes/theme1/bg.png", "name": "Shane Wilson", "lang": "en", "profile_background_tile": false, "favourites_count": 69, "screen_name": "jayquu", "notifications": false, "url": null, "created_at": "Thu Apr 23 16:43:50 +0000 2009", "contributors_enabled": false, "time_zone": "Mountain Time (US & Canada)", "protected": false, "default_profile": true, "is_translator": false}, "geo": null, "in_reply_to_user_id_str": "972651", "lang": "en", "created_at": "Mon Dec 15 02:15:53 +0000 2014", "in_reply_to_status_id_str": "544314234541469696", "place": null}
