{"contributors": null, "truncated": false, "text": "@airberlin @lufthansa @germanwings Danke das Air Berlin und Fly Niki jetzt #4U9529 und #4U2521 \u00fcbernehmen. Ist ja f\u00fcr keine Crew leicht!", "in_reply_to_status_id": 580337440738713600, "id": 580498657843236866, "favorite_count": 2, "source": "<a href=\"http://twitter.com\" rel=\"nofollow\">Twitter Web Client</a>", "retweeted": false, "coordinates": null, "entities": {"symbols": [], "user_mentions": [{"id": 26223583, "indices": [0, 10], "id_str": "26223583", "screen_name": "airberlin", "name": "airberlin"}, {"id": 124476322, "indices": [11, 21], "id_str": "124476322", "screen_name": "lufthansa", "name": "Lufthansa"}, {"id": 26462022, "indices": [22, 34], "id_str": "26462022", "screen_name": "germanwings", "name": "Germanwings"}], "hashtags": [{"indices": [75, 82], "text": "4U9529"}, {"indices": [87, 94], "text": "4U2521"}], "urls": []}, "in_reply_to_screen_name": "airberlin", "id_str": "580498657843236866", "retweet_count": 0, "in_reply_to_user_id": 26223583, "favorited": false, "user": {"follow_request_sent": false, "profile_use_background_image": true, "profile_text_color": "333333", "default_profile_image": false, "id": 1604010308, "profile_background_image_url_https": "https://abs.twimg.com/images/themes/theme18/bg.gif", "verified": false, "profile_location": null, "profile_image_url_https": "https://pbs.twimg.com/profile_images/494557718599204864/zWKAS-5b_normal.jpeg", "profile_sidebar_fill_color": "F6F6F6", "entities": {"description": {"urls": []}}, "followers_count": 73, "profile_sidebar_border_color": "EEEEEE", "id_str": "1604010308", "profile_background_color": "ACDED6", "listed_count": 1, "is_translation_enabled": false, "utc_offset": null, "statuses_count": 661, "description": "Aviation, Chemie, Geschichte, Kultur, Politk, Medien, Verkehr., Konservativ und Opfer des \u00f6sterr. Bildungssystems Au\u00dferdem frei lebender Mensch ;-)", "friends_count": 283, "location": "Wien", "profile_link_color": "044985", "profile_image_url": "http://pbs.twimg.com/profile_images/494557718599204864/zWKAS-5b_normal.jpeg", "following": false, "geo_enabled": false, "profile_banner_url": "https://pbs.twimg.com/profile_banners/1604010308/1406746761", "profile_background_image_url": "http://abs.twimg.com/images/themes/theme18/bg.gif", "name": "Felix Fischer", "lang": "de", "profile_background_tile": false, "favourites_count": 66, "screen_name": "felixfischer99", "notifications": false, "url": null, "created_at": "Thu Jul 18 18:05:36 +0000 2013", "contributors_enabled": false, "time_zone": null, "protected": false, "default_profile": false, "is_translator": false}, "geo": null, "in_reply_to_user_id_str": "26223583", "lang": "de", "created_at": "Tue Mar 24 22:37:19 +0000 2015", "in_reply_to_status_id_str": "580337440738713600", "place": null}
