{"contributors": null, "truncated": false, "text": "@drusamahasan @hahellyer UKrestraint but not as well PM managed,not profuse reassurances for wellbeing for all,not gentle intrractn w public", "in_reply_to_status_id": 544429582418710528, "id": 544433438216814592, "favorite_count": 0, "source": "<a href=\"https://twitter.com/download/android\" rel=\"nofollow\">Twitter for Android Tablets</a>", "retweeted": false, "coordinates": null, "entities": {"symbols": [], "user_mentions": [{"id": 567240884, "indices": [0, 13], "id_str": "567240884", "screen_name": "drusamahasan", "name": "Usama Hasan"}, {"id": 250603308, "indices": [14, 24], "id_str": "250603308", "screen_name": "hahellyer", "name": "H.A. Hellyer  \u062f. \u0625\u062a\u0634"}], "hashtags": [], "urls": []}, "in_reply_to_screen_name": "drusamahasan", "id_str": "544433438216814592", "retweet_count": 0, "in_reply_to_user_id": 567240884, "favorited": false, "user": {"follow_request_sent": false, "profile_use_background_image": true, "profile_text_color": "333333", "default_profile_image": true, "id": 2899924184, "profile_background_image_url_https": "https://abs.twimg.com/images/themes/theme1/bg.png", "verified": false, "profile_location": null, "profile_image_url_https": "https://abs.twimg.com/sticky/default_profile_images/default_profile_3_normal.png", "profile_sidebar_fill_color": "DDEEF6", "entities": {"description": {"urls": []}}, "followers_count": 337, "profile_sidebar_border_color": "C0DEED", "id_str": "2899924184", "profile_background_color": "C0DEED", "listed_count": 15, "is_translation_enabled": false, "utc_offset": 0, "statuses_count": 12445, "description": "", "friends_count": 1602, "location": "", "profile_link_color": "0084B4", "profile_image_url": "http://abs.twimg.com/sticky/default_profile_images/default_profile_3_normal.png", "following": false, "geo_enabled": false, "profile_background_image_url": "http://abs.twimg.com/images/themes/theme1/bg.png", "name": "pcm denault", "lang": "en", "profile_background_tile": false, "favourites_count": 4635, "screen_name": "sunny_pcm", "notifications": false, "url": null, "created_at": "Sat Nov 15 03:48:00 +0000 2014", "contributors_enabled": false, "time_zone": "London", "protected": false, "default_profile": true, "is_translator": false}, "geo": null, "in_reply_to_user_id_str": "567240884", "lang": "en", "created_at": "Mon Dec 15 10:07:01 +0000 2014", "in_reply_to_status_id_str": "544429582418710528", "place": null}
