{"contributors":null,"truncated":false,"text":"The president is upset about the terrorist attack in Paris. It's taking attention away from him.","in_reply_to_status_id":null,"id":553553966970044416,"favorite_count":192,"source":"<a href=\"http:\/\/twitter.com\/download\/iphone\" rel=\"nofollow\">Twitter for iPhone<\/a>","retweeted":false,"coordinates":null,"entities":{"user_mentions":[],"symbols":[],"trends":[],"hashtags":[],"urls":[]},"in_reply_to_screen_name":null,"id_str":"553553966970044416","retweet_count":271,"in_reply_to_user_id":null,"favorited":false,"user":{"follow_request_sent":null,"profile_use_background_image":true,"default_profile_image":false,"id":952112047,"verified":false,"profile_image_url_https":"https:\/\/pbs.twimg.com\/profile_images\/590294499957452800\/12XX2buM_normal.jpg","profile_sidebar_fill_color":"DDEEF6","profile_text_color":"333333","followers_count":48790,"profile_sidebar_border_color":"C0DEED","id_str":"952112047","profile_background_color":"C0DEED","listed_count":778,"profile_background_image_url_https":"https:\/\/abs.twimg.com\/images\/themes\/theme1\/bg.png","utc_offset":-36000,"statuses_count":2494,"description":"Jay Carney's hair & mouth, Josh Earnest's face, Nancy Pelosi's brain, and Obama's honesty.","friends_count":29778,"location":"Parodyville","profile_link_color":"0084B4","profile_image_url":"http:\/\/pbs.twimg.com\/profile_images\/590294499957452800\/12XX2buM_normal.jpg","following":null,"geo_enabled":false,"profile_banner_url":"https:\/\/pbs.twimg.com\/profile_banners\/952112047\/1412037081","profile_background_image_url":"http:\/\/abs.twimg.com\/images\/themes\/theme1\/bg.png","name":"WH PRESS SECRETARY","lang":"en","profile_background_tile":false,"favourites_count":15837,"screen_name":"weknowwhatsbest","notifications":null,"url":null,"created_at":"Fri Nov 16 17:39:25 +0000 2012","contributors_enabled":false,"time_zone":"Hawaii","protected":false,"default_profile":true,"is_translator":false},"geo":null,"in_reply_to_user_id_str":null,"possibly_sensitive":false,"lang":"en","created_at":"Fri Jan 09 14:08:44 +0000 2015","filter_level":"low","in_reply_to_status_id_str":null,"place":null}