{"contributors": null, "truncated": false, "text": "This one is really funny, terrorists want protection to travel. \ud83d\ude02 https://t.co/2U0MnZvZor  @juliamacfarlane", "in_reply_to_status_id": 544425494763302913, "id": 544427349094043648, "favorite_count": 0, "source": "<a href=\"http://twitter.com/download/android\" rel=\"nofollow\">Twitter for Android</a>", "retweeted": false, "coordinates": {"type": "Point", "coordinates": [106.8342423, -6.2063214]}, "entities": {"symbols": [], "user_mentions": [{"id": 20159596, "indices": [91, 107], "id_str": "20159596", "screen_name": "juliamacfarlane", "name": "Julia Macfarlane"}], "hashtags": [], "urls": [{"url": "https://t.co/2U0MnZvZor", "indices": [66, 89], "expanded_url": "https://twitter.com/juliamacfarlane/status/544425494763302913", "display_url": "twitter.com/juliamacfarlan\u2026"}]}, "in_reply_to_screen_name": "juliamacfarlane", "id_str": "544427349094043648", "retweet_count": 0, "in_reply_to_user_id": 20159596, "favorited": false, "user": {"follow_request_sent": false, "profile_use_background_image": true, "profile_text_color": "333333", "default_profile_image": false, "id": 31122446, "profile_background_image_url_https": "https://pbs.twimg.com/profile_background_images/527490535791947776/jxBV1fdh.jpeg", "verified": false, "profile_location": null, "profile_image_url_https": "https://pbs.twimg.com/profile_images/539978392557215745/ox_-ngLE_normal.jpeg", "profile_sidebar_fill_color": "EFEFEF", "entities": {"description": {"urls": []}}, "followers_count": 793, "profile_sidebar_border_color": "FFFFFF", "id_str": "31122446", "profile_background_color": "334433", "listed_count": 14, "is_translation_enabled": false, "utc_offset": 19800, "statuses_count": 14148, "description": "Film Industry", "friends_count": 168, "location": "#Bollywood #Jakarta", "profile_link_color": "009999", "profile_image_url": "http://pbs.twimg.com/profile_images/539978392557215745/ox_-ngLE_normal.jpeg", "following": false, "geo_enabled": true, "profile_banner_url": "https://pbs.twimg.com/profile_banners/31122446/1414596650", "profile_background_image_url": "http://pbs.twimg.com/profile_background_images/527490535791947776/jxBV1fdh.jpeg", "name": "Pramod Naidu", "lang": "en", "profile_background_tile": false, "favourites_count": 4410, "screen_name": "Naidu_Pramod", "notifications": false, "url": null, "created_at": "Tue Apr 14 13:36:41 +0000 2009", "contributors_enabled": false, "time_zone": "Mumbai", "protected": false, "default_profile": false, "is_translator": false}, "geo": {"type": "Point", "coordinates": [-6.2063214, 106.8342423]}, "in_reply_to_user_id_str": "20159596", "possibly_sensitive": true, "lang": "en", "created_at": "Mon Dec 15 09:42:49 +0000 2014", "in_reply_to_status_id_str": "544425494763302913", "place": {"full_name": "Setia Budi, Jakarta Selatan", "url": "https://api.twitter.com/1.1/geo/id/66555622726ab358.json", "country": "Indonesia", "place_type": "city", "bounding_box": {"type": "Polygon", "coordinates": [[[106.817351, -6.24152], [106.852353, -6.24152], [106.852353, -6.201177], [106.817351, -6.201177]]]}, "contained_within": [], "country_code": "ID", "attributes": {}, "id": "66555622726ab358", "name": "Setia Budi"}}
