{"contributors":null,"truncated":false,"text":"@ACLU What can I do if kicked out of McDonalds while protesting via their free wifi? IT HAPPENED TODAY! #OpFerguson @MuhBooLuLu","in_reply_to_status_id":500382073593405442,"id":500720844327649280,"favorite_count":3,"source":"<a href=\"http:\/\/twitter.com\/download\/iphone\" rel=\"nofollow\">Twitter for iPhone<\/a>","retweeted":false,"coordinates":null,"entities":{"symbols":[],"user_mentions":[{"id":13393052,"indices":[0,5],"id_str":"13393052","screen_name":"ACLU","name":"ACLU National"},{"id":1434392514,"indices":[116,127],"id_str":"1434392514","screen_name":"MuhBooLuLu","name":"Eskigga"}],"hashtags":[{"indices":[104,115],"text":"OpFerguson"}],"urls":[]},"in_reply_to_screen_name":"ACLU","id_str":"500720844327649280","retweet_count":1,"in_reply_to_user_id":13393052,"favorited":false,"user":{"follow_request_sent":false,"profile_use_background_image":true,"default_profile_image":false,"id":1905275527,"profile_background_image_url_https":"https:\/\/abs.twimg.com\/images\/themes\/theme1\/bg.png","verified":false,"profile_text_color":"333333","profile_image_url_https":"https:\/\/pbs.twimg.com\/profile_images\/583835722987151360\/EJlTTfyG_normal.jpg","profile_sidebar_fill_color":"DDEEF6","entities":{"description":{"urls":[]}},"followers_count":1567,"profile_sidebar_border_color":"C0DEED","id_str":"1905275527","profile_background_color":"C0DEED","listed_count":23,"is_translation_enabled":false,"utc_offset":-25200,"statuses_count":6894,"description":"Uncaged | Unnaked | Unfamous","friends_count":164,"location":"San Frantokyo, Outer Space","profile_link_color":"169CCC","profile_image_url":"http:\/\/pbs.twimg.com\/profile_images\/583835722987151360\/EJlTTfyG_normal.jpg","following":false,"geo_enabled":true,"profile_banner_url":"https:\/\/pbs.twimg.com\/profile_banners\/1905275527\/1396541593","profile_background_image_url":"http:\/\/abs.twimg.com\/images\/themes\/theme1\/bg.png","screen_name":"wisekrax","lang":"en","profile_background_tile":false,"favourites_count":3066,"name":"Dr. Paul Alinsky Esq","notifications":false,"url":null,"created_at":"Wed Sep 25 19:55:43 +0000 2013","contributors_enabled":false,"time_zone":"Pacific Time (US & Canada)","protected":false,"default_profile":false,"is_translator":false},"geo":null,"in_reply_to_user_id_str":"13393052","lang":"en","created_at":"Sat Aug 16 19:08:46 +0000 2014","in_reply_to_status_id_str":"500382073593405442","place":null}