{"contributors": null, "truncated": false, "text": "@the_stuart_reid yea lets quit our jobs and leave our families to fight them.. That's what the cops govt get paid to do, not avg working ppl", "in_reply_to_status_id": 552811863529246720, "id": 552813477967171584, "favorite_count": 1, "source": "<a href=\"http://twitter.com/download/iphone\" rel=\"nofollow\">Twitter for iPhone</a>", "retweeted": false, "coordinates": null, "entities": {"symbols": [], "user_mentions": [{"id": 66143648, "indices": [0, 16], "id_str": "66143648", "screen_name": "the_stuart_reid", "name": "Stuart Reid"}], "hashtags": [], "urls": []}, "in_reply_to_screen_name": "the_stuart_reid", "id_str": "552813477967171584", "retweet_count": 0, "in_reply_to_user_id": 66143648, "favorited": false, "user": {"follow_request_sent": false, "profile_use_background_image": true, "profile_text_color": "000000", "default_profile_image": false, "id": 150313802, "profile_background_image_url_https": "https://pbs.twimg.com/profile_background_images/319661740/Twitter_wallpaper_1.jpg", "verified": false, "profile_location": null, "profile_image_url_https": "https://pbs.twimg.com/profile_images/554429309830832128/FyrhyLmJ_normal.jpeg", "profile_sidebar_fill_color": "E0AAE0", "entities": {"description": {"urls": []}}, "followers_count": 814, "profile_sidebar_border_color": "000000", "id_str": "150313802", "profile_background_color": "EDADED", "listed_count": 1, "is_translation_enabled": false, "utc_offset": 0, "statuses_count": 17554, "description": "Visitors in the Night..", "friends_count": 289, "location": "I appear missing ", "profile_link_color": "FF00E1", "profile_image_url": "http://pbs.twimg.com/profile_images/554429309830832128/FyrhyLmJ_normal.jpeg", "following": false, "geo_enabled": true, "profile_banner_url": "https://pbs.twimg.com/profile_banners/150313802/1410175758", "profile_background_image_url": "http://pbs.twimg.com/profile_background_images/319661740/Twitter_wallpaper_1.jpg", "name": "Shak\u00e1", "lang": "en", "profile_background_tile": true, "favourites_count": 905, "screen_name": "Necromorph_", "notifications": false, "url": null, "created_at": "Mon May 31 16:33:23 +0000 2010", "contributors_enabled": false, "time_zone": "London", "protected": false, "default_profile": false, "is_translator": false}, "geo": null, "in_reply_to_user_id_str": "66143648", "lang": "en", "created_at": "Wed Jan 07 13:06:18 +0000 2015", "in_reply_to_status_id_str": "552811863529246720", "place": null}
