{"contributors": null, "truncated": false, "text": "@flightradar24 Not at 6,500ft with terrain at 6,300+ ft.", "in_reply_to_status_id": 580325799078793216, "id": 580326007510450176, "favorite_count": 0, "source": "<a href=\"http://twitter.com\" rel=\"nofollow\">Twitter Web Client</a>", "retweeted": false, "coordinates": null, "entities": {"symbols": [], "user_mentions": [{"id": 134196350, "indices": [0, 14], "id_str": "134196350", "screen_name": "flightradar24", "name": "Flightradar24"}], "hashtags": [], "urls": []}, "in_reply_to_screen_name": "flightradar24", "id_str": "580326007510450176", "retweet_count": 0, "in_reply_to_user_id": 134196350, "favorited": false, "user": {"follow_request_sent": false, "profile_use_background_image": false, "profile_text_color": "333333", "default_profile_image": false, "id": 125139513, "profile_background_image_url_https": "https://pbs.twimg.com/profile_background_images/358176900/1972438.jpg", "verified": false, "profile_location": null, "profile_image_url_https": "https://pbs.twimg.com/profile_images/1631988781/LOGO02_normal.jpg", "profile_sidebar_fill_color": "DDEEF6", "entities": {"url": {"urls": [{"url": "http://t.co/sSIacrVIb3", "indices": [0, 22], "expanded_url": "http://TheFlyingEngineer.com", "display_url": "TheFlyingEngineer.com"}]}, "description": {"urls": []}}, "followers_count": 1426, "profile_sidebar_border_color": "C0DEED", "id_str": "125139513", "profile_background_color": "C0DEED", "listed_count": 41, "is_translation_enabled": false, "utc_offset": 19800, "statuses_count": 3620, "description": "Aviation Journalist & Author: Tech & Ops, Aircraft Systems Design Engineer, Instructor, Flight Simulator Designer & Manufacturer, 2 US Patents.", "friends_count": 257, "location": "Bangalore, India", "profile_link_color": "0084B4", "profile_image_url": "http://pbs.twimg.com/profile_images/1631988781/LOGO02_normal.jpg", "following": false, "geo_enabled": false, "profile_banner_url": "https://pbs.twimg.com/profile_banners/125139513/1397113605", "profile_background_image_url": "http://pbs.twimg.com/profile_background_images/358176900/1972438.jpg", "name": "The Flying Engineer", "lang": "en", "profile_background_tile": false, "favourites_count": 748, "screen_name": "TheFlyingEnggnr", "notifications": false, "url": "http://t.co/sSIacrVIb3", "created_at": "Sun Mar 21 20:48:47 +0000 2010", "contributors_enabled": false, "time_zone": "Chennai", "protected": false, "default_profile": false, "is_translator": false}, "geo": null, "in_reply_to_user_id_str": "134196350", "lang": "en", "created_at": "Tue Mar 24 11:11:16 +0000 2015", "in_reply_to_status_id_str": "580325799078793216", "place": null}
