{"contributors":null,"truncated":false,"text":"\u201c@flightradar24: Last position of Germanwings flight #4U9525 at 09:40 UTC\nhttp:\/\/t.co\/BEml4hghRs http:\/\/t.co\/VRBpiRDsZB\u201d\n\nNot good :(","in_reply_to_status_id":580320612155060224,"id":580320698901643264,"favorite_count":1,"source":"<a href=\"http:\/\/itunes.apple.com\/us\/app\/twitter\/id409789998?mt=12\" rel=\"nofollow\">Twitter for Mac<\/a>","retweeted":false,"coordinates":null,"entities":{"symbols":[],"user_mentions":[{"id":134196350,"indices":[1,15],"id_str":"134196350","screen_name":"flightradar24","name":"Flightradar24"}],"hashtags":[{"indices":[53,60],"text":"4U9525"}],"urls":[{"url":"http:\/\/t.co\/BEml4hghRs","indices":[74,96],"expanded_url":"http:\/\/www.flightradar24.com\/data\/airplanes\/d-aipx\/#5d42675","display_url":"flightradar24.com\/data\/airplanes\u2026"}],"media":[{"source_user_id":134196350,"source_status_id_str":"580320612155060224","expanded_url":"http:\/\/twitter.com\/flightradar24\/status\/580320612155060224\/photo\/1","display_url":"pic.twitter.com\/VRBpiRDsZB","url":"http:\/\/t.co\/VRBpiRDsZB","media_url_https":"https:\/\/pbs.twimg.com\/media\/CA22gl6VIAABvha.png","source_user_id_str":"134196350","source_status_id":580320612155060224,"id_str":"580320598049497088","sizes":{"large":{"h":613,"resize":"fit","w":1024},"small":{"h":203,"resize":"fit","w":340},"medium":{"h":359,"resize":"fit","w":600},"thumb":{"h":150,"resize":"crop","w":150}},"indices":[97,119],"type":"photo","id":580320598049497088,"media_url":"http:\/\/pbs.twimg.com\/media\/CA22gl6VIAABvha.png"}]},"in_reply_to_screen_name":"flightradar24","id_str":"580320698901643264","retweet_count":3,"in_reply_to_user_id":134196350,"favorited":false,"user":{"follow_request_sent":false,"profile_use_background_image":true,"profile_text_color":"333333","default_profile_image":false,"id":48032974,"profile_background_image_url_https":"https:\/\/abs.twimg.com\/images\/themes\/theme14\/bg.gif","verified":false,"profile_location":null,"profile_image_url_https":"https:\/\/pbs.twimg.com\/profile_images\/587645147732643840\/X5wAG7XF_normal.jpg","profile_sidebar_fill_color":"EFEFEF","entities":{"url":{"urls":[{"url":"http:\/\/t.co\/aiVjPDj2Gt","indices":[0,22],"expanded_url":"http:\/\/www.arrowfilms.co.uk","display_url":"arrowfilms.co.uk"}]},"description":{"urls":[]}},"followers_count":1693,"profile_sidebar_border_color":"EEEEEE","id_str":"48032974","profile_background_color":"131516","listed_count":15,"is_translation_enabled":false,"utc_offset":3600,"statuses_count":4300,"description":"The roof is not my son... but I will raise it\n\n@ArrowFilms Digital Gentleman","friends_count":1176,"location":"London","profile_link_color":"D1004D","profile_image_url":"http:\/\/pbs.twimg.com\/profile_images\/587645147732643840\/X5wAG7XF_normal.jpg","following":false,"geo_enabled":true,"profile_banner_url":"https:\/\/pbs.twimg.com\/profile_banners\/48032974\/1415662104","profile_background_image_url":"http:\/\/abs.twimg.com\/images\/themes\/theme14\/bg.gif","name":"Alex Anderson","lang":"en","profile_background_tile":true,"favourites_count":283,"screen_name":"alex__anderson","notifications":false,"url":"http:\/\/t.co\/aiVjPDj2Gt","created_at":"Wed Jun 17 17:10:02 +0000 2009","contributors_enabled":false,"time_zone":"London","protected":false,"default_profile":false,"is_translator":false},"geo":null,"in_reply_to_user_id_str":"134196350","possibly_sensitive":false,"possibly_sensitive_appealable":false,"lang":"en","created_at":"Tue Mar 24 10:50:11 +0000 2015","in_reply_to_status_id_str":"580320612155060224","place":null,"extended_entities":{"media":[{"source_user_id":134196350,"source_status_id_str":"580320612155060224","expanded_url":"http:\/\/twitter.com\/flightradar24\/status\/580320612155060224\/photo\/1","display_url":"pic.twitter.com\/VRBpiRDsZB","url":"http:\/\/t.co\/VRBpiRDsZB","media_url_https":"https:\/\/pbs.twimg.com\/media\/CA22gl6VIAABvha.png","source_user_id_str":"134196350","source_status_id":580320612155060224,"id_str":"580320598049497088","sizes":{"large":{"h":613,"resize":"fit","w":1024},"small":{"h":203,"resize":"fit","w":340},"medium":{"h":359,"resize":"fit","w":600},"thumb":{"h":150,"resize":"crop","w":150}},"indices":[97,119],"type":"photo","id":580320598049497088,"media_url":"http:\/\/pbs.twimg.com\/media\/CA22gl6VIAABvha.png"}]}}