{"contributors": null, "truncated": false, "text": "Field near printers has become a makeshift helicopter pad for Puma helicopters #charliehebdo via @RobNisbetSky http://t.co/jKcyL58ohG", "in_reply_to_status_id": 553502311872733184, "id": 553504450569318400, "favorite_count": 9, "source": "<a href=\"http://twitter.com/download/iphone\" rel=\"nofollow\">Twitter for iPhone</a>", "retweeted": false, "coordinates": null, "entities": {"symbols": [], "user_mentions": [{"id": 16591979, "indices": [97, 110], "id_str": "16591979", "screen_name": "RobNisbetSky", "name": "Robert Nisbet"}], "hashtags": [{"indices": [79, 92], "text": "charliehebdo"}], "urls": [], "media": [{"source_user_id": 16591979, "source_status_id_str": "553502311872733184", "expanded_url": "http://twitter.com/RobNisbetSky/status/553502311872733184/photo/1", "display_url": "pic.twitter.com/jKcyL58ohG", "url": "http://t.co/jKcyL58ohG", "media_url_https": "https://pbs.twimg.com/media/B65vW-1CUAAnH8W.jpg", "source_user_id_str": "16591979", "source_status_id": 553502311872733184, "id_str": "553502244826402816", "sizes": {"small": {"h": 255, "resize": "fit", "w": 340}, "large": {"h": 768, "resize": "fit", "w": 1024}, "medium": {"h": 450, "resize": "fit", "w": 600}, "thumb": {"h": 150, "resize": "crop", "w": 150}}, "indices": [111, 133], "type": "photo", "id": 553502244826402816, "media_url": "http://pbs.twimg.com/media/B65vW-1CUAAnH8W.jpg"}]}, "in_reply_to_screen_name": "RobNisbetSky", "id_str": "553504450569318400", "retweet_count": 16, "in_reply_to_user_id": 16591979, "favorited": false, "user": {"follow_request_sent": false, "profile_use_background_image": true, "profile_text_color": "333333", "default_profile_image": false, "id": 2566535282, "profile_background_image_url_https": "https://abs.twimg.com/images/themes/theme1/bg.png", "verified": false, "profile_location": null, "profile_image_url_https": "https://pbs.twimg.com/profile_images/543565392342290432/aXZfchuk_normal.png", "profile_sidebar_fill_color": "DDEEF6", "entities": {"url": {"urls": [{"url": "http://t.co/mUbxGiZt9z", "indices": [0, 22], "expanded_url": "http://www.conflict-news.com", "display_url": "conflict-news.com"}]}, "description": {"urls": []}}, "followers_count": 19638, "profile_sidebar_border_color": "C0DEED", "id_str": "2566535282", "profile_background_color": "C0DEED", "listed_count": 664, "is_translation_enabled": false, "utc_offset": null, "statuses_count": 20083, "description": "Conflict News strives to give you breaking news on conflicts around the world. RT \u2260 Endorsement - Media inquiries can be sent to  rConflictNews at gmail", "friends_count": 758, "location": "", "profile_link_color": "CC4442", "profile_image_url": "http://pbs.twimg.com/profile_images/543565392342290432/aXZfchuk_normal.png", "following": false, "geo_enabled": false, "profile_banner_url": "https://pbs.twimg.com/profile_banners/2566535282/1402735099", "profile_background_image_url": "http://abs.twimg.com/images/themes/theme1/bg.png", "name": "Conflict News", "lang": "en", "profile_background_tile": false, "favourites_count": 4304, "screen_name": "rConflictNews", "notifications": false, "url": "http://t.co/mUbxGiZt9z", "created_at": "Sat Jun 14 05:49:56 +0000 2014", "contributors_enabled": false, "time_zone": null, "protected": false, "default_profile": false, "is_translator": false}, "geo": null, "in_reply_to_user_id_str": "16591979", "possibly_sensitive": false, "lang": "en", "created_at": "Fri Jan 09 10:51:59 +0000 2015", "in_reply_to_status_id_str": "553502311872733184", "place": null, "extended_entities": {"media": [{"source_user_id": 16591979, "source_status_id_str": "553502311872733184", "expanded_url": "http://twitter.com/RobNisbetSky/status/553502311872733184/photo/1", "display_url": "pic.twitter.com/jKcyL58ohG", "url": "http://t.co/jKcyL58ohG", "media_url_https": "https://pbs.twimg.com/media/B65vW-1CUAAnH8W.jpg", "source_user_id_str": "16591979", "source_status_id": 553502311872733184, "id_str": "553502244826402816", "sizes": {"small": {"h": 255, "resize": "fit", "w": 340}, "large": {"h": 768, "resize": "fit", "w": 1024}, "medium": {"h": 450, "resize": "fit", "w": 600}, "thumb": {"h": 150, "resize": "crop", "w": 150}}, "indices": [111, 133], "type": "photo", "id": 553502244826402816, "media_url": "http://pbs.twimg.com/media/B65vW-1CUAAnH8W.jpg"}]}}
